{
  "basic_information": {
    "scholarship_id": 107600,
    "scholarship_name": "Oliver Hodge Memorial Endowed Scholarship",
    "scholarship_code": "S10288",
    "scholarship_notes": "",
    "donor_name": "UCO Foundation",
    "committee_name": "CEPS - Oliver Hodge Memorial Endowed Scholarship",
    "candidate_count": 8
  },
  "renewable_information": {
    "is_renewable": false,
    "renewable_years": 0
  },
  "description": "Scholarship Mission: To provide scholarship assistance to students within the College of Education & Professional Studies who are pursuing a graduate degree in Educational Leadership. Eligibility Requirements This scholarship is open to any student pursuing a graduate degree in Educational Leadership Minimum 2.75 GPA Demonstrates through a personal statement a desire to continue working in the Oklahoma Public School System Selection Process Recipients of the scholarship will be selected by a departmental committee Award Requirements Must be enrolled in the upcoming fall and spring semester to receive award Attendance at an awards banquet is required for all recipients Recipients must write a thank you letter to the donors of the scholarship",
  "general_criteria": {
    "description": "Soft requirements that provide additional points/consideration",
    "criteria_count": 0,
    "criteria": [],
    "total_possible_points": 0,
    "banner_summary": {
      "total_criteria": 0,
      "banner_accessible": 0,
      "application_required": 0,
      "manual_review": 0
    }
  },
  "conditional_criteria": {
    "description": "Requirements for scholarship renewal",
    "criteria_count": 0,
    "criteria": []
  },
  "metadata": {
    "processed_date": "2025-08-28T14:17:39.816658",
    "source_file": "ScholarshipswithCriteriaNextGen08202025.csv",
    "processing_notes": {
      "html_cleaned": true,
      "requirements_parsed": true,
      "criteria_categorized": true
    }
  },
  "hard_criteria": {
    "description": "Hard requirements that must be met to qualify for the scholarship",
    "criteria_count": 6,
    "criteria": [
      {
        "id": 1,
        "type": "unknown",
        "description": "SIS_College is Education and Prof Studies",
        "raw_text": "SIS_College is Education and Prof Studies",
        "banner_accessibility": "banner_accessible"
      },
      {
        "id": 2,
        "type": "level",
        "description": "SIS_Level is Graduate",
        "raw_text": "SIS_Level is Graduate",
        "banner_accessibility": "banner_accessible"
      },
      {
        "id": 3,
        "type": "major",
        "description": "SIS_Major is Educational Leadership   or SIS_Major is Educational Administration",
        "raw_text": "SIS_Major is Educational Leadership   or SIS_Major is Educational Administration",
        "parsed_sis": {
          "majors": [
            "Educational Administration",
            "Educational Leadership"
          ],
          "minors": [],
          "classifications": [],
          "gpa_requirements": [],
          "other_sis": []
        },
        "clean_description": "Major: Educational Administration, Educational Leadership",
        "banner_accessibility": "banner_accessible"
      },
      {
        "id": 4,
        "type": "gpa",
        "description": "SIS_CumGPA >= 2.75",
        "raw_text": "SIS_CumGPA >= 2.75",
        "banner_accessibility": "banner_accessible"
      },
      {
        "id": 5,
        "type": "application",
        "description": "Complete Essay \"CEPS_Ed_Leadership\"",
        "raw_text": "Complete Essay \"CEPS_Ed_Leadership\"",
        "banner_accessibility": "manual_review"
      },
      {
        "id": 6,
        "type": "application",
        "description": "Complete Application: \"UCO Foundation Qualifying Scholarship Application\"",
        "raw_text": "Complete Application: \"UCO Foundation Qualifying Scholarship Application\"",
        "banner_accessibility": "manual_review"
      }
    ],
    "banner_summary": {
      "total_criteria": 6,
      "banner_accessible": 4,
      "application_required": 0,
      "manual_review": 2
    }
  },
  "progress_status": "not-processed"
}