{
  "basic_information": {
    "scholarship_id": 151389,
    "scholarship_name": "Clint Rohr and Brian Gorrell Endowed Scholarship in Jazz Studies- NOMINATION",
    "scholarship_code": "S10546",
    "scholarship_notes": "",
    "donor_name": "UCO Foundation",
    "committee_name": "",
    "candidate_count": 0
  },
  "renewable_information": {
    "is_renewable": false,
    "renewable_years": 0
  },
  "description": "The recipient(s) of the Clint Rohr and Brian Gorrell Endowed Scholarship in Jazz Studies will be selected by faculty nomination. The recipient(s) will be selected in the spring for distribution the following fall and spring semesters. Eligibility Requirements Recipient must be nominated and selected by members of the jazz studies division faculty Open to fulltime undergraduate or graduate students of sophomore level or above Minimum 2.0 GPA",
  "general_criteria": {
    "description": "Soft requirements that provide additional points/consideration",
    "criteria_count": 0,
    "criteria": [],
    "total_possible_points": 0,
    "banner_summary": {
      "total_criteria": 0,
      "banner_accessible": 0,
      "application_required": 0,
      "manual_review": 0
    }
  },
  "conditional_criteria": {
    "description": "Requirements for scholarship renewal",
    "criteria_count": 0,
    "criteria": []
  },
  "metadata": {
    "processed_date": "2025-08-28T14:17:39.706136",
    "source_file": "ScholarshipswithCriteriaNextGen08202025.csv",
    "processing_notes": {
      "html_cleaned": true,
      "requirements_parsed": true,
      "criteria_categorized": true
    }
  },
  "hard_criteria": {
    "description": "Hard requirements that must be met to qualify for the scholarship",
    "criteria_count": 0,
    "criteria": [],
    "banner_summary": {
      "total_criteria": 0,
      "banner_accessible": 0,
      "application_required": 0,
      "manual_review": 0
    }
  },
  "progress_status": "not-processed"
}